fastapi_web_session/__init__.py
fastapi_web_session/_logger.py
fastapi_web_session/constants.py
fastapi_web_session/dependencies.py
fastapi_web_session/enabled_session.py
fastapi_web_session/redis.py
fastapi_web_session/session.py
fastapi_web_session/storage.py
tests/__init__.py
tests/conftest.py
tests/test_constants.py
tests/test_session.py
tests/test_storage.py
fastapi_web_session-0.1.0a2.dist-info/LICENSE
fastapi_web_session-0.1.0a2.dist-info/METADATA
fastapi_web_session-0.1.0a2.dist-info/WHEEL
fastapi_web_session-0.1.0a2.dist-info/top_level.txt
fastapi_web_session-0.1.0a2.dist-info/RECORD
