Metadata-Version: 2.1
Name: fastapi-web-session
Version: 0.1.0a2
Summary: web sessions for FastAPI
Home-page: https://github.com/amenezes/fastapi-web-session
Author: Alexandre Menezes
Author-email: alexandre.fmenezes@gmail.com
License: Apache-2.0
Project-URL: Documentation, https://github.com/amenezes/fastapi-web-session
Project-URL: Code, https://github.com/amenezes/fastapi-web-session
Project-URL: Issue tracker, https://github.com/amenezes/fastapi-web-session/issues
Project-URL: Changes, https://github.com/amenezes/fastapi-web-session/releases
Keywords: "FastAPI","session","Redis"
Classifier: Development Status :: 5 - Production/Stable
Classifier: Framework :: AsyncIO
Classifier: Framework :: FastAPI
Classifier: Intended Audience :: Developers
Classifier: License :: OSI Approved :: Apache Software License
Classifier: Operating System :: OS Independent
Classifier: Programming Language :: Python :: 3 :: Only
Classifier: Programming Language :: Python :: 3.8
Classifier: Programming Language :: Python :: 3.9
Classifier: Programming Language :: Python :: 3.10
Classifier: Programming Language :: Python :: Implementation :: CPython
Classifier: Topic :: Software Development :: Libraries
Classifier: Topic :: Internet :: WWW/HTTP :: Session
Requires-Python: >=3.8
License-File: LICENSE
Requires-Dist: fastapi (>=0.85.0)
Requires-Dist: redis (==4.3.4)
Provides-Extra: all
Requires-Dist: mkdocs-material ; extra == 'all'
Provides-Extra: docs
Requires-Dist: mkdocs-material ; extra == 'docs'
